opentelemetry/exporter/cloud_monitoring/__init__.py
opentelemetry/exporter/cloud_monitoring/version.py
opentelemetry_exporter_cloud_monitoring-0.10b1.dist-info/METADATA
opentelemetry_exporter_cloud_monitoring-0.10b1.dist-info/WHEEL
opentelemetry_exporter_cloud_monitoring-0.10b1.dist-info/top_level.txt
opentelemetry_exporter_cloud_monitoring-0.10b1.dist-info/RECORD
