Metadata-Version: 2.1
Name: opentelemetry-exporter-cloud-monitoring
Version: 0.10b1
Summary: Deprecated Cloud Monitoring integration for OpenTelemetry
Home-page: https://github.com/open-telemetry/opentelemetry-python/ext/opentelemetry-exporter-cloud-monitoring
Author: OpenTelemetry Authors
Author-email: cncf-opentelemetry-contributors@lists.cncf.io
License: Apache-2.0
Platform: any
Classifier: Development Status :: 4 - Beta
Classifier: Intended Audience :: Developers
Classifier: License :: OSI Approved :: Apache Software License
Classifier: Programming Language :: Python
Classifier: Programming Language :: Python :: 3
Classifier: Programming Language :: Python :: 3.4
Classifier: Programming Language :: Python :: 3.5
Classifier: Programming Language :: Python :: 3.6
Classifier: Programming Language :: Python :: 3.7
Requires-Python: >=3.4
Requires-Dist: google-cloud-monitoring
Requires-Dist: opentelemetry-api
Requires-Dist: opentelemetry-sdk
Provides-Extra: test
